PySideExtn/RoundProgressBar.py
PySideExtn/SpiralProgressBar.py
PySideExtn/__init__.py
PySideExtn/demo/__init__.py
PySideExtn/demo/demo.py
PySideExtn/examples/__init__.py
PySideExtn-2.0.2.dist-info/LICENSE
PySideExtn-2.0.2.dist-info/METADATA
PySideExtn-2.0.2.dist-info/WHEEL
PySideExtn-2.0.2.dist-info/top_level.txt
PySideExtn-2.0.2.dist-info/RECORD
