Metadata-Version: 2.1
Name: PySideExtn
Version: 2.0.2
Summary: PySideExtn is an open-source Python programming language extension designed to empower PySide2, PyQt5, PySide6 or PyQt6 users with an expanded toolkit. This extension enriches the PySide2, PyQt5, PySide6 or PyQt6 library by introducing a range of additional widgets and features, significantly enhancing its capabilities and versatility.
Home-page: https://github.com/KhamisiKibet/PySideExtn
Author: ANJAL.P. Improved by Khamisi Kibet
Author-email: spinncompany@gmail.com
Keywords: PySide,PyQt,animation,custom,widgets,QML,C++,QT Creator,Moder GUI,Desktop GUI,Design
Classifier: Development Status :: 5 - Production/Stable
Classifier: Intended Audience :: Developers
Classifier: Programming Language :: Python :: 3.5
Classifier: Programming Language :: Python :: 3.6
Classifier: Programming Language :: Python :: 3.7
Classifier: Programming Language :: Python :: 3.8
Classifier: Programming Language :: Python :: 3.9
Classifier: License :: OSI Approved :: MIT License
Classifier: Operating System :: OS Independent
Requires-Python: >=3.6
License-File: LICENSE
Requires-Dist: qtpy
